compas_skeleton/__init__.py
compas_skeleton/datastructures/__init__.py
compas_skeleton/datastructures/skeleton.py
compas_skeleton/rhino/__init__.py
compas_skeleton/scene/__init__.py
compas_skeleton-2.0.1.dist-info/AUTHORS.md
compas_skeleton-2.0.1.dist-info/LICENSE
compas_skeleton-2.0.1.dist-info/METADATA
compas_skeleton-2.0.1.dist-info/WHEEL
compas_skeleton-2.0.1.dist-info/top_level.txt
compas_skeleton-2.0.1.dist-info/RECORD
